pyvinecopulib/__init__.py
pyvinecopulib/__init__.pyi
pyvinecopulib/_python_helpers/__init__.py
pyvinecopulib/_python_helpers/bicop.py
pyvinecopulib/_python_helpers/kde1d.py
pyvinecopulib/_python_helpers/stats.py
pyvinecopulib/_python_helpers/vinecop.py
pyvinecopulib/pair_copuladata.py
pyvinecopulib/py.typed
pyvinecopulib/pyvinecopulib_ext.cp310-win_amd64.pyd
pyvinecopulib-0.7.5.dist-info/METADATA
pyvinecopulib-0.7.5.dist-info/WHEEL
pyvinecopulib-0.7.5.dist-info/licenses/LICENSE
pyvinecopulib-0.7.5.dist-info/RECORD
