Metadata-Version: 2.1
Name: pyvinecopulib
Version: 0.7.5
Summary: A python interface to vinecopulib
Keywords: copula,vines copulas,pair-copulas constructions
Author-Email: Thibault Vatter <info@vinecopulib.com>, Thomas Nagler <info@vinecopulib.com>
License: The MIT License (MIT)
Classifier: Development Status :: 3 - Alpha
Classifier: Intended Audience :: Financial and Insurance Industry
Classifier: Intended Audience :: Healthcare Industry
Classifier: Intended Audience :: Information Technology
Classifier: Intended Audience :: Other Audience
Classifier: Intended Audience :: Science/Research
Classifier: Intended Audience :: Telecommunications Industry
Classifier: Topic :: Scientific/Engineering
Classifier: Topic :: Scientific/Engineering :: Mathematics
Classifier: Programming Language :: C++
Classifier: Programming Language :: Python :: 3.9
Classifier: Programming Language :: Python :: 3.10
Classifier: Programming Language :: Python :: 3.11
Classifier: Programming Language :: Python :: 3.12
Classifier: Programming Language :: Python :: 3.13
Classifier: Programming Language :: Python :: 3.14
Classifier: License :: OSI Approved :: MIT License
Project-URL: Homepage, https://github.com/vinecopulib/pyvinecopulib/
Project-URL: Documentation, https://vinecopulib.github.io/pyvinecopulib
Project-URL: Repository, https://github.com/vinecopulib/pyvinecopulib.git
Project-URL: Issues, https://github.com/vinecopulib/pyvinecopulib/issues
Requires-Python: >=3.9
Requires-Dist: numpy>=1.14
Requires-Dist: matplotlib>=3.0
Requires-Dist: networkx>=3.0
Requires-Dist: pydot>=3.0
Provides-Extra: dev
Requires-Dist: mypy>=1.15; extra == "dev"
Requires-Dist: ruff==0.11.6; extra == "dev"
Requires-Dist: pytest>=8.0; extra == "dev"
Requires-Dist: pytest-rerunfailures; extra == "dev"
Requires-Dist: pytest-xdist>=3.6; extra == "dev"
Requires-Dist: nbmake; extra == "dev"
Requires-Dist: pre-commit; extra == "dev"
Requires-Dist: pytest-cov; extra == "dev"
Requires-Dist: coverage[toml]; extra == "dev"
Provides-Extra: examples
Requires-Dist: jupyterlab; extra == "examples"
Requires-Dist: scipy; extra == "examples"
Provides-Extra: doc
Requires-Dist: sphinx==7.0; extra == "doc"
Requires-Dist: nbsphinx==0.9.2; extra == "doc"
Requires-Dist: sphinx-rtd-theme; extra == "doc"
Requires-Dist: sphinx-autodoc-typehints; extra == "doc"
Requires-Dist: myst-parser; extra == "doc"
